MANIFEST.in
README.md
setup.py
src/ryzom_django_mui.py
src/ryzom_muicss.py
src/py2js/__init__.py
src/py2js/formater.py
src/py2js/renderer.py
src/py2js/transpiler.py
src/py2js/static/py2js.js
src/ryzom/__init__.py
src/ryzom/components.py
src/ryzom/html.py
src/ryzom/test.py
src/ryzom.egg-info/PKG-INFO
src/ryzom.egg-info/SOURCES.txt
src/ryzom.egg-info/dependency_links.txt
src/ryzom.egg-info/requires.txt
src/ryzom.egg-info/top_level.txt
src/ryzom/bundle/__init__.py
src/ryzom/bundle/css.py
src/ryzom/bundle/js.py
src/ryzom/components/mdc.py
src/ryzom/contrib/django.py
src/ryzom_django/__init__.py
src/ryzom_django/apps.py
src/ryzom_django/bundle.py
src/ryzom_django/forms.py
src/ryzom_django/html.py
src/ryzom_django/manage.py
src/ryzom_django/template_backend.py
src/ryzom_django/urls.py
src/ryzom_django/management/__init__.py
src/ryzom_django/management/commands/__init__.py
src/ryzom_django/management/commands/ryzom_bundle.py
src/ryzom_django/management/commands/ryzom_css.py
src/ryzom_django/management/commands/ryzom_js.py
src/ryzom_django_channels/__init__.py
src/ryzom_django_channels/apps.py
src/ryzom_django_channels/components.py
src/ryzom_django_channels/consumers.py
src/ryzom_django_channels/ddp.py
src/ryzom_django_channels/methods.py
src/ryzom_django_channels/models.py
src/ryzom_django_channels/pubsub.py
src/ryzom_django_channels/routing.py
src/ryzom_django_channels/signals.py
src/ryzom_django_channels/views.py
src/ryzom_django_channels/migrations/0001_initial.py
src/ryzom_django_channels/migrations/0002_remove_unused_fields.py
src/ryzom_django_channels/migrations/__init__.py
src/ryzom_django_channels/static/ryzom.js
src/ryzom_django_channels_example/models.py
src/ryzom_django_channels_example/views.py
src/ryzom_django_channels_example/migrations/0001_initial.py
src/ryzom_django_channels_example/migrations/__init__.py
src/ryzom_django_example/__init__.py
src/ryzom_django_example/asgi.py
src/ryzom_django_example/settings.py
src/ryzom_django_example/urls.py
src/ryzom_django_example/views.py
src/ryzom_django_example/wsgi.py
src/ryzom_django_mdc/__init__.py
src/ryzom_django_mdc/apps.py
src/ryzom_django_mdc/forms.py
