Metadata-Version: 2.1
Name: ryzom
Version: 0.6.7
Summary: Meteorish Python responsive frontend
Home-page: https://yourlabs.io/oss/ryzom
Author: Thomas Mignot
Author-email: jamespic@gmail.com
License: UNKNOWN
Keywords: python frontend
Platform: UNKNOWN
Classifier: Development Status :: 1 - Planning
Classifier: Environment :: Web Environment
Classifier: Framework :: Django
Classifier: Intended Audience :: Developers
Classifier: License :: OSI Approved :: MIT License
Classifier: Operating System :: OS Independent
Classifier: Programming Language :: Python
Classifier: Programming Language :: Python :: 3
Classifier: Topic :: Internet :: WWW/HTTP
Classifier: Topic :: Software Development :: Libraries :: Python Modules
Requires-Python: >=3
Provides-Extra: project
